celery_pubsub/__init__.py
celery_pubsub/pubsub.py
celery_pubsub-1.0.2.dist-info/LICENSE
celery_pubsub-1.0.2.dist-info/METADATA
celery_pubsub-1.0.2.dist-info/WHEEL
celery_pubsub-1.0.2.dist-info/top_level.txt
celery_pubsub-1.0.2.dist-info/RECORD
