Metadata-Version: 2.1
Name: celery-pubsub
Version: 1.0.2
Summary: A Publish and Subscribe library for Celery
Home-page: https://github.com/Mulugruntz/celery-pubsub
Author: Samuel GIFFARD
Author-email: mulugruntz@gmail.com
License: MIT
Download-URL: https://github.com/Mulugruntz/celery-pubsub/tarball/1.0.2
Keywords: celery,publish,subscribe,pubsub
Platform: UNKNOWN
Classifier: Development Status :: 5 - Production/Stable
Classifier: Intended Audience :: Developers
Classifier: License :: OSI Approved :: MIT License
Classifier: Programming Language :: Python :: 2.7
Classifier: Programming Language :: Python :: 3.5
Classifier: Programming Language :: Python :: 3.6
Classifier: Programming Language :: Python :: 3.7
Classifier: Programming Language :: Python :: 3.8
Classifier: Programming Language :: Python :: 3.9
Classifier: Programming Language :: Python :: 3.10
Classifier: Programming Language :: Python :: Implementation :: CPython
Classifier: Programming Language :: Python :: Implementation :: PyPy
Classifier: Topic :: Software Development :: Libraries
Classifier: Topic :: System :: Distributed Computing
Classifier: Topic :: Utilities
License-File: LICENSE
Requires-Dist: celery (>=3.1.0)
